ymaps/__init__.py
ymaps/api_parameters.py
ymaps/asynchr.py
ymaps/exceptions.py
ymaps/settings.py
ymaps/sync.py
ymaps-1.2.dist-info/LICENSE
ymaps-1.2.dist-info/WHEEL
ymaps-1.2.dist-info/METADATA
ymaps-1.2.dist-info/RECORD
