Metadata-Version: 2.1
Name: ymaps
Version: 1.2
Summary: Client for Yandex Maps API
Author-email: sfkan6 <sfkan6@yandex.ru>
Requires-Python: >=3.7
Classifier: Programming Language :: Python :: 3
Classifier: License :: OSI Approved :: MIT License
Requires-Dist: httpx>=0.23.0
Project-URL: Home, https://github.com/sfkan6/ymaps
